Metadata-Version: 1.1
Name: kmeansfordemo
Version: 1.0
Summary: kmeans
Home-page: UNKNOWN
Author: abhi
Author-email: abhi@yahoo.com
License: MIT
Platform: UNKNOWN
Classifier: Development Status :: 4 - Beta
Classifier: Intended Audience :: Developers
Classifier: License :: OSI Approved :: MIT License
Classifier: Programming Language :: Python :: 2.7
Classifier: Programming Language :: Python :: 3
